gentraframe/config.py
gentraframe/evaluator.py
gentraframe/evaluatorv2.py
gentraframe/experiment.py
gentraframe/extension.py
gentraframe/extensionv2.py
gentraframe/gen_random_mask_v8.py
gentraframe/gradient_clipping.py
gentraframe/pipeline.py
gentraframe/pipelinev2.py
gentraframe/trainer.py
gentraframe/trainerv2.py
gentraframe/utils.py
gentraframe-0.1.5.dist-info/LICENSE
gentraframe-0.1.5.dist-info/METADATA
gentraframe-0.1.5.dist-info/WHEEL
gentraframe-0.1.5.dist-info/RECORD
